Metadata-Version: 1.0
Name: Stat-distributions-test101
Version: 1.0
Summary: Gaussian distributions and Binomial Distributions
Home-page: UNKNOWN
Author: UNKNOWN
Author-email: UNKNOWN
License: UNKNOWN
Platform: UNKNOWN
